cms_boilerplate
startproject
