Metadata-Version: 1.1
Name: django-cms-boilerplate
Version: 1.0beta3
Summary: Django-cms initial project template
Home-page: http://packages.python.org/cms-boilerplate
Author: Benjamin Brinkman
Author-email: ben@benjaminbrinkman.com
License: MIT
Keywords: cms boilerplate django web
Platform: UNKNOWN
Classifier: Development Status :: 4 - Beta
Classifier: Topic :: Utilities
Classifier: License :: OSI Approved :: MIT License
